MANIFEST.in
README.txt
VERSION.txt
ez_setup.py
setup.cfg
setup.py
docs/Makefile
docs/source/API.rst
docs/source/News.rst
docs/source/conf.py
docs/source/index.rst
docs/source/Manual/GettingStarted.rst
docs/source/Manual/Protecting.rst
docs/source/Manual/index.rst
docs/source/_static/logo_hi.gif
docs/source/_static/repoze.css
repoze/__init__.py
repoze.what_pylons.egg-info/PKG-INFO
repoze.what_pylons.egg-info/SOURCES.txt
repoze.what_pylons.egg-info/dependency_links.txt
repoze.what_pylons.egg-info/entry_points.txt
repoze.what_pylons.egg-info/namespace_packages.txt
repoze.what_pylons.egg-info/not-zip-safe
repoze.what_pylons.egg-info/requires.txt
repoze.what_pylons.egg-info/top_level.txt
repoze/what/__init__.py
repoze/what/plugins/__init__.py
repoze/what/plugins/pylonshq/__init__.py
repoze/what/plugins/pylonshq/protectors.py
repoze/what/plugins/pylonshq/utils.py