Metadata-Version: 1.0
Name: repoze.what-pylons
Version: 1.0b3
Summary: The repoze.what v1 plugin for Pylons/TG2 integration
Home-page: http://code.gustavonarea.net/repoze.what-pylons/
Author: Gustavo Narea
Author-email: repoze-dev@lists.repoze.org
License: BSD-derived (http://www.repoze.org/LICENSE.txt)
Keywords: web application wsgi server pylons turbogears authorization repoze
Platform: UNKNOWN
Classifier: Development Status :: 4 - Beta
Classifier: Environment :: Web Environment
Classifier: Framework :: Pylons
Classifier: Framework :: TurboGears
Classifier: Intended Audience :: Developers
Classifier: Natural Language :: English
Classifier: Operating System :: OS Independent
Classifier: Programming Language :: Python
Classifier: Topic :: Database
Classifier: Topic :: Internet :: WWW/HTTP :: WSGI
Classifier: Topic :: Security
